hack4u/__init__.py
hack4u/cursos.py
hack4u/utils.py
hack4u_sammy_ulfh-0.1.1.dist-info/METADATA
hack4u_sammy_ulfh-0.1.1.dist-info/WHEEL
hack4u_sammy_ulfh-0.1.1.dist-info/top_level.txt
hack4u_sammy_ulfh-0.1.1.dist-info/RECORD
