Metadata-Version: 2.1
Name: hack4u_sammy-ulfh
Version: 0.1.1
Summary: Una biblioteca para consultar cursos de hack4u.
Home-page: https://hack4u.io
Author: Sammy-ulfh
